vllm_haystack/__about__.py
vllm_haystack/__init__.py
vllm_haystack-0.1.2.dist-info/METADATA
vllm_haystack-0.1.2.dist-info/WHEEL
vllm_haystack-0.1.2.dist-info/licenses/LICENSE
vllm_haystack-0.1.2.dist-info/RECORD
