Metadata-Version: 2.1
Name: vllm-haystack
Version: 0.1.2
Summary: A simple adapter to use vLLM in your Haystack pipelines. 
Project-URL: Documentation, https://github.com/LLukas22/vLLM-haystack-adapter#readme
Project-URL: Issues, https://github.com/LLukas22/vLLM-haystack-adapter/issues
Project-URL: Source, https://github.com/LLukas22/vLLM-haystack-adapter
Author-email: Lukas Kreussel <65088241+LLukas22@users.noreply.github.com>
License-Expression: MIT
License-File: LICENSE
Keywords: AI,Haystack,LLM,NLP
Classifier: Development Status :: 4 - Beta
Classifier: Programming Language :: Python
Classifier: Programming Language :: Python :: 3.7
Classifier: Programming Language :: Python :: 3.8
Classifier: Programming Language :: Python :: 3.9
Classifier: Programming Language :: Python :: 3.10
Classifier: Programming Language :: Python :: 3.11
Classifier: Programming Language :: Python :: Implementation :: CPython
Classifier: Programming Language :: Python :: Implementation :: PyPy
Requires-Python: >=3.7
Requires-Dist: farm-haystack>=1.20.0
Requires-Dist: requests>=2.31.0
Requires-Dist: sseclient>=0.0.27
Requires-Dist: tokenizers>=0.13.3
